qparser/__init__.py
qparser-0.1a3.dist-info/LICENSE
qparser-0.1a3.dist-info/METADATA
qparser-0.1a3.dist-info/WHEEL
qparser-0.1a3.dist-info/top_level.txt
qparser-0.1a3.dist-info/RECORD
