Metadata-Version: 2.1
Name: qparser
Version: 0.1a3
Summary: Query Parser
Author-email: "@bbc6502" <c0d3@gpobox.net>
Project-URL: Homepage, https://github.com/bbc6502/qparser
Project-URL: Bug Tracker, https://github.com/bbc6502/qparser/issues
Classifier: Programming Language :: Python :: 3
Classifier: License :: OSI Approved :: MIT License
Classifier: Operating System :: OS Independent
Requires-Python: >=3.7
License-File: LICENSE
